{
  "worker": {
    "id": "1.14.50",
    "worker_account": "1.2.121",
    "work_begin_date": "2017-02-02T00:00:00",
    "work_end_date": "2017-02-17T00:00:00",
    "daily_pay": 100000,
    "worker": [
      1,
      {
        "balance": "1.13.1186"
      }
    ],
    "vote_for": "2:202",
    "vote_against": "2:203",
    "total_votes_for": "1532924544667",
    "total_votes_against": 0,
    "name": "agree to increase witness payment to 4BTS/block",
    "url": "https://github.com/bitshares/bsips/issues/22",
    "worker_account_details": {
      "id": "1.2.121",
      "membership_expiration_date": "1969-12-31T23:59:59",
      "registrar": "1.2.121",
      "referrer": "1.2.121",
      "lifetime_referrer": "1.2.121",
      "network_fee_percentage": 2000,
      "lifetime_referrer_fee_percentage": 8000,
      "referrer_rewards_percentage": 0,
      "name": "bitcrab",
      "owner": {
        "weight_threshold": 3,
        "account_auths": [
          [
            "1.2.964",
            1
          ],
          [
            "1.2.149047",
            1
          ],
          [
            "1.2.152878",
            2
          ]
        ],
        "key_auths": [],
        "address_auths": []
      },
      "active": {
        "weight_threshold": 1,
        "account_auths": [],
        "key_auths": [
          [
            "BTS7JFp7uKFTiKfmR8XkWtdGozdLJB2m9y6awXWjBKUeBs5EkS6mw",
            1
          ]
        ],
        "address_auths": []
      },
      "options": {
        "memo_key": "BTS7JFp7uKFTiKfmR8XkWtdGozdLJB2m9y6awXWjBKUeBs5EkS6mw",
        "voting_account": "1.2.5",
        "num_witness": 45,
        "num_committee": 11,
        "votes": [
          "1:23",
          "1:25",
          "1:26",
          "1:27",
          "1:31",
          "1:32",
          "1:33",
          "1:34",
          "1:36",
          "1:37",
          "1:38",
          "1:39",
          "1:40",
          "1:42",
          "1:43",
          "1:45",
          "1:48",
          "1:49",
          "1:51",
          "1:52",
          "1:55",
          "1:56",
          "1:57",
          "1:63",
          "2:65",
          "1:75",
          "1:77",
          "1:83",
          "0:85",
          "0:87",
          "0:88",
          "0:91",
          "0:111",
          "0:112",
          "1:114",
          "0:141",
          "1:143",
          "0:147",
          "1:162",
          "1:163",
          "1:164",
          "1:165",
          "1:166",
          "1:169",
          "1:170",
          "0:173",
          "1:185",
          "1:190",
          "1:191",
          "2:194",
          "1:196",
          "0:213",
          "1:214",
          "1:216",
          "1:218",
          "1:219",
          "0:223",
          "2:224",
          "2:233",
          "1:235",
          "2:246",
          "2:251",
          "2:258",
          "2:260",
          "2:262",
          "2:264",
          "2:266"
        ],
        "extensions": []
      },
      "statistics": {
        "id": "2.6.121",
        "owner": "1.2.121",
        "most_recent_op": "2.9.110735431",
        "total_ops": 1482,
        "removed_ops": 482,
        "total_core_in_orders": 165562098,
        "lifetime_fees_paid": "35659673407",
        "pending_fees": 0,
        "pending_vested_fees": 0
      },
      "whitelisting_accounts": [],
      "blacklisting_accounts": [],
      "whitelisted_accounts": [],
      "blacklisted_accounts": [],
      "cashback_vb": "1.13.282",
      "owner_special_authority": [
        0,
        {}
      ],
      "active_special_authority": [
        0,
        {}
      ],
      "top_n_control_flags": 0,
      "registrar_name": "bitcrab",
      "referrer_name": "bitcrab",
      "lifetime_referrer_name": "bitcrab",
      "votes": [
        {
          "id": "1.6.13",
          "witness_account": "1.2.31890",
          "last_aslot": 16530591,
          "signing_key": "BTS8S4fV6Zvx5BNErD15WSxQmQd1VgsmyhtjH5fMdo5aUPDyHhgVz",
          "pay_vb": "1.13.22",
          "vote_id": "1:23",
          "total_votes": "30350412729753",
          "url": "https://github.com/roadscape",
          "total_missed": 1719,
          "last_confirmed_block_num": 16425169
        },
        {
          "id": "1.6.15",
          "witness_account": "1.2.333",
          "last_aslot": 20413663,
          "signing_key": "BTS63FhVfsSnZtu7ocrS1WE2bfrTZUP7rxy7ZEW6xXNkyXTGLbc4H",
          "pay_vb": "1.13.24",
          "vote_id": "1:25",
          "total_votes": "30880058137313",
          "url": "\"\"",
          "total_missed": 2316,
          "last_confirmed_block_num": 20284401
        },
        {
          "id": "1.6.16",
          "witness_account": "1.2.167",
          "last_aslot": 23221922,
          "signing_key": "BTS6D2dhWchBN9EFRDZ8tZYiHFN1WcJvLV1hg7P53xo2N73DYJg2t",
          "pay_vb": "1.13.32",
          "vote_id": "1:26",
          "total_votes": "48330448666036",
          "url": ".",
          "total_missed": 3609,
          "last_confirmed_block_num": 23081651
        },
        {
          "id": "1.6.17",
          "witness_account": "1.2.25010",
          "last_aslot": 23221901,
          "signing_key": "BTS6wV9VeA5RabRaQi1Dwn94BcpcYNxZ51XQmJ3NVAdpziZaxffZJ",
          "pay_vb": "1.13.34",
          "vote_id": "1:27",
          "total_votes": "78394561262357",
          "url": "",
          "total_missed": 1577,
          "last_confirmed_block_num": 23081631
        },
        {
          "id": "1.6.21",
          "witness_account": "1.2.28788",
          "last_aslot": 23221906,
          "signing_key": "BTS5ARpXg6yWZptHgik721dyXek57v53op6XT7rwTj7Kmb8CGwWEM",
          "pay_vb": "1.13.35",
          "vote_id": "1:31",
          "total_votes": "43547515234383",
          "url": "http://bts-witness.quisquis.de/",
          "total_missed": 3539,
          "last_confirmed_block_num": 23081636
        },
        {
          "id": "1.6.22",
          "witness_account": "1.2.564",
          "last_aslot": 23221897,
          "signing_key": "BTS86RmbRTt6g5mY2mnWyCEJRYLu5NyqnoFd42cCZYQCi4nYWV4xS",
          "pay_vb": "1.13.36",
          "vote_id": "1:32",
          "total_votes": "69010117403272",
          "url": "",
          "total_missed": 2257,
          "last_confirmed_block_num": 23081627
        },
        {
          "id": "1.6.23",
          "witness_account": "1.2.3284",
          "last_aslot": 20741654,
          "signing_key": "BTS8CRvjYMQBqFxnpagkX7WXWxEGBuM11Ft219WvZhhNAYXT3LsTR",
          "pay_vb": "1.13.49",
          "vote_id": "1:33",
          "total_votes": "31079495971562",
          "url": "-",
          "total_missed": 5809,
          "last_confirmed_block_num": 20612211
        },
        {
          "id": "1.6.24",
          "witness_account": "1.2.10285",
          "last_aslot": 22759768,
          "signing_key": "BTS7yYqVQZ3BB31T2P3Cot4M2Eyxo59aMLhrAvKUi54YWBJcpzAdj",
          "pay_vb": "1.13.47",
          "vote_id": "1:34",
          "total_votes": "35682182596005",
          "url": "http://agsexplorer.com",
          "total_missed": 7657,
          "last_confirmed_block_num": 22620610
        },
        {
          "id": "1.6.26",
          "witness_account": "1.2.23043",
          "last_aslot": 23215831,
          "signing_key": "BTS7W9Ekx5vUi1uwLH7rtSFbTRdpQboE4jMukfgW4dGpwNH9ZKHrb",
          "pay_vb": "1.13.48",
          "vote_id": "1:36",
          "total_votes": "40689951781344",
          "url": "http://bit.ly/ihashfury",
          "total_missed": 869,
          "last_confirmed_block_num": 23075852
        },
        {
          "id": "1.6.27",
          "witness_account": "1.2.29205",
          "last_aslot": 23221904,
          "signing_key": "BTS5CBBJDrwus41WRDdh4reEbJpgh9fVqBG4Vd7oScPVejj5LHBBU",
          "pay_vb": "1.13.46",
          "vote_id": "1:37",
          "total_votes": "42963208888089",
          "url": "bitshares.kr",
          "total_missed": 5198,
          "last_confirmed_block_num": 23081634
        },
        {
          "id": "1.6.28",
          "witness_account": "1.2.30889",
          "last_aslot": 23221923,
          "signing_key": "BTS66qci9rpf9p87cHuqHdVtDUKAubLx9U5TDkneBnTkqs72Eheqv",
          "pay_vb": "1.13.59",
          "vote_id": "1:38",
          "total_votes": "70235013980650",
          "url": "https://github.com/lafona/delegate-1.lafona",
          "total_missed": 4396,
          "last_confirmed_block_num": 23081652
        },
        {
          "id": "1.6.29",
          "witness_account": "1.2.32321",
          "last_aslot": 1481861,
          "signing_key": "BTS8R6yT22snMyVGXtJkvr9w6kb2uXSbYa3GJzrnHoZN4AmdYBrVD",
          "pay_vb": "1.13.60",
          "vote_id": "1:39",
          "total_votes": "35410777614554",
          "url": "2.0.160103b",
          "total_missed": 118,
          "last_confirmed_block_num": 1474230
        },
        {
          "id": "1.6.30",
          "witness_account": "1.2.32495",
          "last_aslot": 13964202,
          "signing_key": "BTS8ZWNd9K82gPqKVDbkK8etaYTBMQ3ME3MTQ6HqF586ZbMLrZ5DH",
          "pay_vb": "1.13.129",
          "vote_id": "1:40",
          "total_votes": "30701512068132",
          "url": "bitspace.no",
          "total_missed": 2208,
          "last_confirmed_block_num": 13884680
        },
        {
          "id": "1.6.32",
          "witness_account": "1.2.31965",
          "last_aslot": 992317,
          "signing_key": "BTS8Pr7paLBxGL84YUeA9GdnRHZij1XA1oBPDbvuMRYt12Yx3LTCU",
          "pay_vb": "1.13.96",
          "vote_id": "1:42",
          "total_votes": "35202510545712",
          "url": "",
          "total_missed": 86,
          "last_confirmed_block_num": 984911
        },
        {
          "id": "1.6.33",
          "witness_account": "1.2.89292",
          "last_aslot": 36504,
          "signing_key": "BTS5VBUnDrNXPJWNnbcZx2xbUCC5JD6TrfMCmPzhVrW8Dx3KeT7Fc",
          "pay_vb": "1.13.65",
          "vote_id": "1:43",
          "total_votes": "35591989990548",
          "url": "",
          "total_missed": 29,
          "last_confirmed_block_num": 33845
        },
        {
          "id": "1.6.35",
          "witness_account": "1.2.35248",
          "last_aslot": 23221898,
          "signing_key": "BTS5hEKbh1FhVfmbfmtEaQ8diQ5MK1W14z6tBGWSPV879sg6pxzu8",
          "pay_vb": "1.13.128",
          "vote_id": "1:45",
          "total_votes": "89344043430139",
          "url": "https://github.com/abitmore",
          "total_missed": 711,
          "last_confirmed_block_num": 23081628
        },
        {
          "id": "1.6.38",
          "witness_account": "1.2.10091",
          "last_aslot": 18322522,
          "signing_key": "BTS6oRYTjcbQU8s9TAtEY4qZknY7Xaw3E29ore3L3xX611KxFE5Nr",
          "pay_vb": "1.13.256",
          "vote_id": "1:48",
          "total_votes": "40862059589925",
          "url": "url-to-proposal",
          "total_missed": 2519,
          "last_confirmed_block_num": 18199109
        },
        {
          "id": "1.6.39",
          "witness_account": "1.2.6956",
          "last_aslot": 0,
          "signing_key": "BTS6JhLDwYRKSa7FjEmfhy4VHHMn8SZySc8RJrbc5mWyCvERV3coy",
          "vote_id": "1:49",
          "total_votes": "34499608863755",
          "url": "",
          "total_missed": 0,
          "last_confirmed_block_num": 0
        },
        {
          "id": "1.6.40",
          "witness_account": "1.2.23836",
          "last_aslot": 20520202,
          "signing_key": "BTS87mX5Fk4JHGMCudKYeTo2HfsukkLM9GyBYpj1QHwR2jxy7Mp7a",
          "pay_vb": "1.13.179",
          "vote_id": "1:51",
          "total_votes": "28395246551954",
          "url": "http://blocktrades.us/",
          "total_missed": 5486,
          "last_confirmed_block_num": 20390816
        },
        {
          "id": "1.6.41",
          "witness_account": "1.2.90109",
          "last_aslot": 784018,
          "signing_key": "BTS6eBmHNheafXGKgcdWEikjQnEd8hqUsepgCVcPUUraex9vFR8gX",
          "pay_vb": "1.13.317",
          "vote_id": "1:52",
          "total_votes": "35006817563732",
          "url": "http://merkabahnk.io/os/",
          "total_missed": 0,
          "last_confirmed_block_num": 776901
        },
        {
          "id": "1.6.44",
          "witness_account": "1.2.13774",
          "last_aslot": 965995,
          "signing_key": "BTS8Jr9MQE61fZUa9tRvSYcFQRRr8j2baWouknxjRbPkpVtNACa9m",
          "pay_vb": "1.13.238",
          "vote_id": "1:55",
          "total_votes": "35496637161014",
          "url": "url-to-proposal",
          "total_missed": 266,
          "last_confirmed_block_num": 958591
        },
        {
          "id": "1.6.45",
          "witness_account": "1.2.31810",
          "last_aslot": 23221918,
          "signing_key": "BTS8XW8yetT7CqXH8J1VmJXxbP16SWQPm8M2ZHuppWhbfjuCQwveD",
          "pay_vb": "1.13.166",
          "vote_id": "1:56",
          "total_votes": "66213864156458",
          "url": "",
          "total_missed": 2079,
          "last_confirmed_block_num": 23081648
        },
        {
          "id": "1.6.46",
          "witness_account": "1.2.95289",
          "last_aslot": 992328,
          "signing_key": "BTS6YAzxhwoZmFUFjsbo4PTfDr57HDwoQx5EgEGs7CCT41nXvHXYF",
          "pay_vb": "1.13.186",
          "vote_id": "1:57",
          "total_votes": "35496627547184",
          "url": "http://www.dragonball",
          "total_missed": 260,
          "last_confirmed_block_num": 984922
        },
        {
          "id": "1.6.52",
          "witness_account": "1.2.36614",
          "last_aslot": 0,
          "signing_key": "BTS6wLW6bQqirb2cMnmjY4ZKCs984ZC4vshZYVCa5AbUdDrHbTF5w",
          "vote_id": "1:63",
          "total_votes": "35761946715673",
          "url": "banx.io",
          "total_missed": 0,
          "last_confirmed_block_num": 0
        },
        {
          "id": "1.14.0",
          "worker_account": "1.2.90742",
          "work_begin_date": "2015-10-20T17:30:00",
          "work_end_date": "2035-12-31T00:00:00",
          "daily_pay": "40000000000",
          "worker": [
            0,
            {
              "total_burned": "17998209685898"
            }
          ],
          "vote_for": "2:65",
          "vote_against": "2:66",
          "total_votes_for": "54125103565992",
          "total_votes_against": 0,
          "name": "refund400k",
          "url": ""
        },
        {
          "id": "1.6.54",
          "witness_account": "1.2.93394",
          "last_aslot": 0,
          "signing_key": "BTS8ReAgz5uR6tjX1bQQiCUgZZQmWzW5355VdHiRvxcvSVod4Wetb",
          "vote_id": "1:75",
          "total_votes": "35080771510298",
          "url": "witness.bar.com",
          "total_missed": 0,
          "last_confirmed_block_num": 0
        },
        {
          "id": "1.6.55",
          "witness_account": "1.2.14002",
          "last_aslot": 0,
          "signing_key": "BTS6Ppd2uCY3yrrsiEsSXhCCGiSs8WotZ4ri6qWu4R68hs5sw8vTo",
          "vote_id": "1:77",
          "total_votes": "35078035392269",
          "url": "url-to-proposal",
          "total_missed": 0,
          "last_confirmed_block_num": 0
        },
        {
          "id": "1.6.56",
          "witness_account": "1.2.121",
          "last_aslot": 0,
          "signing_key": "BTS6pfAWjugRdA2ayVH5ksZ8DCge8cUzL4xfxzpec7h8Q37QJ9ea7",
          "vote_id": "1:83",
          "total_votes": "35343485519539",
          "url": "",
          "total_missed": 0,
          "last_confirmed_block_num": 0
        },
        {
          "id": "1.5.15",
          "committee_member_account": "1.2.121",
          "vote_id": "0:85",
          "total_votes": "87535825080212",
          "url": "transwiser.com"
        },
        {
          "id": "1.5.16",
          "committee_member_account": "1.2.25010",
          "vote_id": "0:87",
          "total_votes": "68971238312465",
          "url": ""
        },
        {
          "id": "1.5.17",
          "committee_member_account": "1.2.8891",
          "vote_id": "0:88",
          "total_votes": "67070114414321",
          "url": "bitshares.kr"
        },
        {
          "id": "1.5.20",
          "committee_member_account": "1.2.97845",
          "vote_id": "0:91",
          "total_votes": "67519018212681",
          "url": "http://www.bunkerchainlabs.com"
        },
        {
          "id": "1.5.22",
          "committee_member_account": "1.2.3284",
          "vote_id": "0:111",
          "total_votes": "37088073999983",
          "url": "-"
        },
        {
          "id": "1.5.23",
          "committee_member_account": "1.2.159",
          "vote_id": "0:112",
          "total_votes": "47003808865224",
          "url": "ebitrose.com"
        },
        {
          "id": "1.6.58",
          "witness_account": "1.2.10423",
          "last_aslot": 0,
          "signing_key": "BTS8VudFJunqArjsM1XbGv9EAdSP73Whm859WdxcjmpbmwbDhzEss",
          "vote_id": "1:114",
          "total_votes": "35552984746579",
          "url": "www.bitsharestalk.org",
          "total_missed": 0,
          "last_confirmed_block_num": 0
        },
        {
          "id": "1.5.25",
          "committee_member_account": "1.2.12376",
          "vote_id": "0:141",
          "total_votes": "85678084748556",
          "url": "https://github.com/abitmore"
        },
        {
          "id": "1.6.59",
          "witness_account": "1.2.14035",
          "last_aslot": 23221902,
          "signing_key": "BTS7sanqxmPfZZ4Z6ETzMnxNxay79e41kwJ1QJ1maHUkq3Gcpgd2z",
          "pay_vb": "1.13.854",
          "vote_id": "1:143",
          "total_votes": "79544630606632",
          "url": "https://btsgo.net",
          "total_missed": 2821,
          "last_confirmed_block_num": 23081632
        },
        {
          "id": "1.5.27",
          "committee_member_account": "1.2.282",
          "vote_id": "0:147",
          "total_votes": "74971867129812",
          "url": "http://bitshares.eu"
        },
        {
          "id": "1.6.61",
          "witness_account": "1.2.102867",
          "last_aslot": 0,
          "signing_key": "BTS5opfTZM9YVsTmdPNqhp4DTEE1rjFhXBZCq6TysRtZGvQrqB7q9",
          "vote_id": "1:162",
          "total_votes": "35078720125816",
          "url": "http://witness.mayega.com",
          "total_missed": 0,
          "last_confirmed_block_num": 0
        },
        {
          "id": "1.6.62",
          "witness_account": "1.2.102928",
          "last_aslot": 0,
          "signing_key": "BTS4wuYcFprN4q9Un6zkVo8qtHvFWC6Qex83B42rsArxBC6VXvGop",
          "vote_id": "1:163",
          "total_votes": "35079408251239",
          "url": " ",
          "total_missed": 0,
          "last_confirmed_block_num": 0
        },
        {
          "id": "1.6.63",
          "witness_account": "1.2.31359",
          "last_aslot": 23221916,
          "signing_key": "BTS64VtxZum6GMV3T4zWLZMYYTyoXV5fe3enkomDGCCB55FJaUDzf",
          "pay_vb": "1.13.763",
          "vote_id": "1:164",
          "total_votes": "52965856082316",
          "url": "https://bitsharestalk.org",
          "total_missed": 4861,
          "last_confirmed_block_num": 23081646
        },
        {
          "id": "1.6.64",
          "witness_account": "1.2.2850",
          "last_aslot": 23221911,
          "signing_key": "BTS7euVUZg96FzihMGLJGnh2tUtKGqiS2spQUQMCGu2TD99HKDHVx",
          "pay_vb": "1.13.778",
          "vote_id": "1:165",
          "total_votes": "57041349011557",
          "url": "https://yoyow.org/",
          "total_missed": 1642,
          "last_confirmed_block_num": 23081641
        },
        {
          "id": "1.6.65",
          "witness_account": "1.2.4952",
          "last_aslot": 23221919,
          "signing_key": "BTS8QjC5GnhKinPKNfEprAJirYywRrGZ83P32Z5Rsjr9k5xnFZgjf",
          "pay_vb": "1.13.815",
          "vote_id": "1:166",
          "total_votes": "60226515773954",
          "url": "http://www.btsabc.org/",
          "total_missed": 1274,
          "last_confirmed_block_num": 23081649
        },
        {
          "id": "1.6.66",
          "witness_account": "1.2.99609",
          "last_aslot": 0,
          "signing_key": "BTS6PGGRA8hvg7N3tLqXrYKHQcztSgCL93JCGc5pT2Beef1urnT4T",
          "vote_id": "1:169",
          "total_votes": "35741104987708",
          "url": "http://bitett.com/",
          "total_missed": 0,
          "last_confirmed_block_num": 0
        },
        {
          "id": "1.6.67",
          "witness_account": "1.2.110851",
          "last_aslot": 0,
          "signing_key": "BTS7oLLQhcifEcfWZrQkR8RCYRAdvG5WhBUMikCSvDUXttW7ciQht",
          "vote_id": "1:170",
          "total_votes": "35153158146722",
          "url": "https://bitsharestalk.org/index.php/topic,22504.0.html",
          "total_missed": 0,
          "last_confirmed_block_num": 0
        },
        {
          "id": "1.5.28",
          "committee_member_account": "1.2.35939",
          "vote_id": "0:173",
          "total_votes": "46316052044964",
          "url": "https://bitsharestalk.org/index.php/topic,22516.0.html"
        },
        {
          "id": "1.6.68",
          "witness_account": "1.2.115062",
          "last_aslot": 0,
          "signing_key": "BTS5XPJGmjXhwBTCEP963k29eBHRnayPT87Q6DUzbochw63Sw72bM",
          "vote_id": "1:185",
          "total_votes": "34974481672103",
          "url": "https://nexusdev.us/",
          "total_missed": 0,
          "last_confirmed_block_num": 0
        },
        {
          "id": "1.6.69",
          "witness_account": "1.2.130258",
          "last_aslot": 23221900,
          "signing_key": "BTS5XfJVbe2NEcmgUF9cv2J3gCm6LPbyiTM2dVom4EnSxizjeVn8s",
          "pay_vb": "1.13.1043",
          "vote_id": "1:190",
          "total_votes": "80932284640636",
          "url": "http://www.weibo.com/callmeluc",
          "total_missed": 9190,
          "last_confirmed_block_num": 23081630
        },
        {
          "id": "1.6.70",
          "witness_account": "1.2.134261",
          "last_aslot": 15323352,
          "signing_key": "BTS8UUcPeZ8hxAuN2xEtu1DPWnHYJy894kQASf1E3Xmh3oXbfBwQu",
          "pay_vb": "1.13.1230",
          "vote_id": "1:191",
          "total_votes": "29489593286507",
          "url": "http://richlist.btsabc.org",
          "total_missed": 564,
          "last_confirmed_block_num": 15231407
        },
        {
          "id": "1.14.47",
          "worker_account": "1.2.138721",
          "work_begin_date": "2016-11-09T00:00:00",
          "work_end_date": "2017-12-31T23:59:59",
          "daily_pay": 1000000000,
          "worker": [
            1,
            {
              "balance": "1.13.1090"
            }
          ],
          "vote_for": "2:194",
          "vote_against": "2:195",
          "total_votes_for": "27179874121805",
          "total_votes_against": 0,
          "name": "Project administration & essential maintenance",
          "url": "https://bitsharestalk.org/index.php/topic,23495.0.html"
        },
        {
          "id": "1.6.71",
          "witness_account": "1.2.130210",
          "last_aslot": 23221921,
          "signing_key": "BTS6nDkh4ZBLNMsfb3dY2NLtz4NWPGskk4tHNJH6JPqfFJiqh34pG",
          "pay_vb": "1.13.1151",
          "vote_id": "1:196",
          "total_votes": "82216753910303",
          "url": "https://bitsharestalk.org/index.php/topic,23628.0.html",
          "total_missed": 3557,
          "last_confirmed_block_num": 23081650
        },
        {
          "id": "1.5.30",
          "committee_member_account": "1.2.158781",
          "vote_id": "0:213",
          "total_votes": "54243211508567",
          "url": "https://bitsharestalk.org/index.php/topic,23931.0.html"
        },
        {
          "id": "1.6.74",
          "witness_account": "1.2.133999",
          "last_aslot": 23221917,
          "signing_key": "BTS7Q2wS9rhqrkY7nAGNMG5MqscSUTY7gupwTQAybcEjUB77vD9a4",
          "pay_vb": "1.13.1286",
          "vote_id": "1:214",
          "total_votes": "76701265635392",
          "url": "https://bitsharestalk.org/index.php/topic,24017.msg304832.html",
          "total_missed": 30,
          "last_confirmed_block_num": 23081647
        },
        {
          "id": "1.6.75",
          "witness_account": "1.2.152739",
          "last_aslot": 23221912,
          "signing_key": "BTS5ffxzUfM52pA5nHZ7TCHGUeQxmi6shJCrnXX45Ns75soyPBDDt",
          "pay_vb": "1.13.1337",
          "vote_id": "1:216",
          "total_votes": "75162919746734",
          "url": "https://steemit.com/blockchain/@blockchained/bitshares-wintess-proposal-vote-for-blckchnd",
          "total_missed": 919,
          "last_confirmed_block_num": 23081642
        },
        {
          "id": "1.6.76",
          "witness_account": "1.2.158783",
          "last_aslot": 23221924,
          "signing_key": "BTS6t9nirTdNfmiegVK5dQRUABooP6RLPNXyjxdStFP8qhtQnKR4d",
          "pay_vb": "1.13.1304",
          "vote_id": "1:218",
          "total_votes": "60646224460530",
          "url": "https://bitsharestalk.org/index.php/topic,23992.0.html",
          "total_missed": 613,
          "last_confirmed_block_num": 23081653
        },
        {
          "id": "1.6.77",
          "witness_account": "1.2.155674",
          "last_aslot": 0,
          "signing_key": "BTS7LPJTYQ4bqyZUgvjPp9wBJ81P8NVjacTgTJNyjhWgyRZ3zbr5P",
          "vote_id": "1:219",
          "total_votes": "34927298543085",
          "url": "http://witness.bar.com/",
          "total_missed": 0,
          "last_confirmed_block_num": 0
        },
        {
          "id": "1.5.33",
          "committee_member_account": "1.2.130258",
          "vote_id": "0:223",
          "total_votes": "79202548861090",
          "url": "http://www.weibo.com/callmeluc"
        },
        {
          "id": "1.14.55",
          "worker_account": "1.2.356589",
          "work_begin_date": "2017-07-12T00:00:00",
          "work_end_date": "2018-01-08T00:00:00",
          "daily_pay": 218700000,
          "worker": [
            1,
            {
              "balance": "1.13.1608"
            }
          ],
          "vote_for": "2:224",
          "vote_against": "2:225",
          "total_votes_for": "83999325916096",
          "total_votes_against": 0,
          "name": "Alfredo Garcia - Core Developer for the second half of 2017",
          "url": "https://github.com/oxarbitrage/worker-proposals/blob/master/bitshares2017.md"
        },
        {
          "id": "1.14.58",
          "worker_account": "1.2.364315",
          "work_begin_date": "2017-08-15T00:00:00",
          "work_end_date": "2018-02-15T00:00:00",
          "daily_pay": 1400000000,
          "worker": [
            1,
            {
              "balance": "1.13.1737"
            }
          ],
          "vote_for": "2:233",
          "vote_against": "2:234",
          "total_votes_for": "83474189238807",
          "total_votes_against": 0,
          "name": "201708-bitsharesui",
          "url": "http://www.bitshares.foundation/workers/2017-08-bill-butler"
        },
        {
          "id": "1.6.84",
          "witness_account": "1.2.369",
          "last_aslot": 23221903,
          "signing_key": "BTS6naPodhtnvgTyfMu9vzjv7N9nac22mz9c2Co4d3otDS3jZ6kLD",
          "pay_vb": "1.13.1851",
          "vote_id": "1:235",
          "total_votes": "67750103852213",
          "url": "https://github.com/crazybits",
          "total_missed": 458,
          "last_confirmed_block_num": 23081633
        },
        {
          "id": "1.14.61",
          "worker_account": "1.2.364315",
          "work_begin_date": "2017-10-18T00:00:00",
          "work_end_date": "2018-12-31T00:00:00",
          "daily_pay": 450000000,
          "worker": [
            1,
            {
              "balance": "1.13.2115"
            }
          ],
          "vote_for": "2:246",
          "vote_against": "2:247",
          "total_votes_for": "77858094523969",
          "total_votes_against": 0,
          "name": "201710-spokesperson",
          "url": "None"
        },
        {
          "id": "1.14.63",
          "worker_account": "1.2.449675",
          "work_begin_date": "2017-11-01T00:00:00",
          "work_end_date": "2018-05-01T00:00:00",
          "daily_pay": 939200000,
          "worker": [
            1,
            {
              "balance": "1.13.2198"
            }
          ],
          "vote_for": "2:251",
          "vote_against": "2:252",
          "total_votes_for": "58337205371631",
          "total_votes_against": 0,
          "name": "BitShares Greater China Representative",
          "url": "https://steemit.com/bitshares/@lzmlam/bts-greater-china-representative-worker-proposal-bilingual"
        },
        {
          "id": "1.14.66",
          "worker_account": "1.2.459901",
          "work_begin_date": "2017-12-01T00:00:00",
          "work_end_date": "2018-03-31T23:59:00",
          "daily_pay": 206000000,
          "worker": [
            1,
            {
              "balance": "1.13.2299"
            }
          ],
          "vote_for": "2:258",
          "vote_against": "2:259",
          "total_votes_for": "82046282832528",
          "total_votes_against": 0,
          "name": "Abit - Core Developer - 201712~201803",
          "url": "https://github.com/abitmore/bts-worker-proposals/blob/master/abit-worker-201712-201803.md"
        },
        {
          "id": "1.14.67",
          "worker_account": "1.2.364315",
          "work_begin_date": "2017-12-01T00:00:00",
          "work_end_date": "2018-05-31T00:00:00",
          "daily_pay": 270000000,
          "worker": [
            1,
            {
              "balance": "1.13.2307"
            }
          ],
          "vote_for": "2:260",
          "vote_against": "2:261",
          "total_votes_for": "73267324418661",
          "total_votes_against": 0,
          "name": "201712-infrastructure",
          "url": "http://www.bitshares.foundation/workers/2017-12-infrastructure"
        },
        {
          "id": "1.14.68",
          "worker_account": "1.2.364315",
          "work_begin_date": "2017-12-01T00:00:00",
          "work_end_date": "2018-05-31T00:00:00",
          "daily_pay": 250000000,
          "worker": [
            1,
            {
              "balance": "1.13.2325"
            }
          ],
          "vote_for": "2:262",
          "vote_against": "2:263",
          "total_votes_for": "63579308607169",
          "total_votes_against": 0,
          "name": "2017-12-blockchainacademy",
          "url": "http://www.bitshares.foundation/workers/2017-12-blockchainacademy"
        },
        {
          "id": "1.14.69",
          "worker_account": "1.2.12376",
          "work_begin_date": "2018-01-01T00:00:00",
          "work_end_date": "2018-05-01T00:00:00",
          "daily_pay": 100000,
          "worker": [
            1,
            {
              "balance": "1.13.2355"
            }
          ],
          "vote_for": "2:264",
          "vote_against": "2:265",
          "total_votes_for": "65814750821765",
          "total_votes_against": 0,
          "name": "Poll - BSIP26 - Refund Original Order Creation Fee on Cancel",
          "url": "https://github.com/bitshares/bsips/blob/master/bsip-0026.md"
        },
        {
          "id": "1.14.70",
          "worker_account": "1.2.12376",
          "work_begin_date": "2018-01-01T00:00:00",
          "work_end_date": "2018-05-01T00:00:00",
          "daily_pay": 100000,
          "worker": [
            1,
            {
              "balance": "1.13.2356"
            }
          ],
          "vote_for": "2:266",
          "vote_against": "2:267",
          "total_votes_for": "65094862484483",
          "total_votes_against": 0,
          "name": "Poll - BSIP27 - Asset Issuer Reclaim Fee Pool Funds",
          "url": "https://github.com/bitshares/bsips/blob/master/bsip-0027.md"
        }
      ],
      "cashback_balance": {
        "id": "1.13.282",
        "owner": "1.2.121",
        "balance": {
          "amount": 5283741,
          "asset_id": "1.3.0"
        },
        "policy": [
          1,
          {
            "vesting_seconds": 7776000,
            "start_claim": "1970-01-01T00:00:00",
            "coin_seconds_earned": "41086370016000",
            "coin_seconds_earned_last_update": "2017-12-29T14:00:00"
          }
        ]
      },
      "balances": [
        {
          "id": "2.5.3283",
          "owner": "1.2.121",
          "asset_type": "1.3.0",
          "balance": 6028732
        },
        {
          "id": "2.5.3292",
          "owner": "1.2.121",
          "asset_type": "1.3.106",
          "balance": 903
        },
        {
          "id": "2.5.3287",
          "owner": "1.2.121",
          "asset_type": "1.3.113",
          "balance": 100
        },
        {
          "id": "2.5.3285",
          "owner": "1.2.121",
          "asset_type": "1.3.121",
          "balance": 11
        },
        {
          "id": "2.5.3290",
          "owner": "1.2.121",
          "asset_type": "1.3.136",
          "balance": 99
        },
        {
          "id": "2.5.3293",
          "owner": "1.2.121",
          "asset_type": "1.3.140",
          "balance": 80000
        },
        {
          "id": "2.5.11177",
          "owner": "1.2.121",
          "asset_type": "1.3.221",
          "balance": 200
        },
        {
          "id": "2.5.3288",
          "owner": "1.2.121",
          "asset_type": "1.3.338",
          "balance": 0
        },
        {
          "id": "2.5.3289",
          "owner": "1.2.121",
          "asset_type": "1.3.369",
          "balance": 50000
        },
        {
          "id": "2.5.7294",
          "owner": "1.2.121",
          "asset_type": "1.3.431",
          "balance": "5000000000"
        },
        {
          "id": "2.5.3291",
          "owner": "1.2.121",
          "asset_type": "1.3.432",
          "balance": "58201984821"
        },
        {
          "id": "2.5.3286",
          "owner": "1.2.121",
          "asset_type": "1.3.535",
          "balance": 5606955
        },
        {
          "id": "2.5.3284",
          "owner": "1.2.121",
          "asset_type": "1.3.538",
          "balance": 23162
        },
        {
          "id": "2.5.9072",
          "owner": "1.2.121",
          "asset_type": "1.3.569",
          "balance": 397
        },
        {
          "id": "2.5.6998",
          "owner": "1.2.121",
          "asset_type": "1.3.628",
          "balance": "300000000000"
        },
        {
          "id": "2.5.7916",
          "owner": "1.2.121",
          "asset_type": "1.3.659",
          "balance": 187000000
        },
        {
          "id": "2.5.7308",
          "owner": "1.2.121",
          "asset_type": "1.3.734",
          "balance": 0
        },
        {
          "id": "2.5.7761",
          "owner": "1.2.121",
          "asset_type": "1.3.746",
          "balance": 0
        },
        {
          "id": "2.5.21497",
          "owner": "1.2.121",
          "asset_type": "1.3.758",
          "balance": 14288
        },
        {
          "id": "2.5.11947",
          "owner": "1.2.121",
          "asset_type": "1.3.825",
          "balance": 888880000
        },
        {
          "id": "2.5.12919",
          "owner": "1.2.121",
          "asset_type": "1.3.839",
          "balance": 81214
        },
        {
          "id": "2.5.28313",
          "owner": "1.2.121",
          "asset_type": "1.3.850",
          "balance": 503022
        },
        {
          "id": "2.5.31332",
          "owner": "1.2.121",
          "asset_type": "1.3.1005",
          "balance": 92254537
        },
        {
          "id": "2.5.149923",
          "owner": "1.2.121",
          "asset_type": "1.3.1007",
          "balance": 10000000
        },
        {
          "id": "2.5.26619",
          "owner": "1.2.121",
          "asset_type": "1.3.1018",
          "balance": 1
        },
        {
          "id": "2.5.29144",
          "owner": "1.2.121",
          "asset_type": "1.3.1032",
          "balance": 1000000
        },
        {
          "id": "2.5.36636",
          "owner": "1.2.121",
          "asset_type": "1.3.1042",
          "balance": 0
        },
        {
          "id": "2.5.47610",
          "owner": "1.2.121",
          "asset_type": "1.3.1165",
          "balance": 100000
        },
        {
          "id": "2.5.41890",
          "owner": "1.2.121",
          "asset_type": "1.3.1169",
          "balance": "767588106114"
        },
        {
          "id": "2.5.157443",
          "owner": "1.2.121",
          "asset_type": "1.3.1868",
          "balance": 1000
        },
        {
          "id": "2.5.151711",
          "owner": "1.2.121",
          "asset_type": "1.3.2107",
          "balance": 10000000
        },
        {
          "id": "2.5.162237",
          "owner": "1.2.121",
          "asset_type": "1.3.2220",
          "balance": 44504
        },
        {
          "id": "2.5.168521",
          "owner": "1.2.121",
          "asset_type": "1.3.2236",
          "balance": 18500000
        },
        {
          "id": "2.5.214366",
          "owner": "1.2.121",
          "asset_type": "1.3.2482",
          "balance": 50000000
        },
        {
          "id": "2.5.290398",
          "owner": "1.2.121",
          "asset_type": "1.3.2616",
          "balance": 700
        }
      ],
      "vesting_balances": [
        {
          "id": "1.13.282",
          "owner": "1.2.121",
          "balance": {
            "amount": 5283741,
            "asset_id": "1.3.0"
          },
          "policy": [
            1,
            {
              "vesting_seconds": 7776000,
              "start_claim": "1970-01-01T00:00:00",
              "coin_seconds_earned": "41086370016000",
              "coin_seconds_earned_last_update": "2017-12-29T14:00:00"
            }
          ]
        },
        {
          "id": "1.13.830",
          "owner": "1.2.121",
          "balance": {
            "amount": 0,
            "asset_id": "1.3.0"
          },
          "policy": [
            1,
            {
              "vesting_seconds": 86400,
              "start_claim": "1970-01-01T00:00:00",
              "coin_seconds_earned": "0",
              "coin_seconds_earned_last_update": "2016-06-01T00:00:00"
            }
          ]
        },
        {
          "id": "1.13.1186",
          "owner": "1.2.121",
          "balance": {
            "amount": 0,
            "asset_id": "1.3.0"
          },
          "policy": [
            1,
            {
              "vesting_seconds": 86400,
              "start_claim": "1970-01-01T00:00:00",
              "coin_seconds_earned": "0",
              "coin_seconds_earned_last_update": "2017-02-01T15:03:42"
            }
          ]
        },
        {
          "id": "1.13.1187",
          "owner": "1.2.121",
          "balance": {
            "amount": 0,
            "asset_id": "1.3.0"
          },
          "policy": [
            1,
            {
              "vesting_seconds": 86400,
              "start_claim": "1970-01-01T00:00:00",
              "coin_seconds_earned": "0",
              "coin_seconds_earned_last_update": "2017-02-01T15:05:30"
            }
          ]
        }
      ],
      "limit_orders": [],
      "call_orders": [
        {
          "id": "1.8.1320",
          "borrower": "1.2.121",
          "collateral": 162057000,
          "debt": 10000,
          "call_price": {
            "base": {
              "amount": 46302,
              "asset_id": "1.3.0"
            },
            "quote": {
              "amount": 5,
              "asset_id": "1.3.121"
            }
          }
        },
        {
          "id": "1.8.15057",
          "borrower": "1.2.121",
          "collateral": 3505098,
          "debt": 20090,
          "call_price": {
            "base": {
              "amount": 7010196,
              "asset_id": "1.3.0"
            },
            "quote": {
              "amount": 70315,
              "asset_id": "1.3.780"
            }
          }
        }
      ],
      "settle_orders": [],
      "proposals": [],
      "assets": [
        "1.3.780",
        "1.3.1014",
        "1.3.1015",
        "1.3.1032",
        "1.3.1220",
        "1.3.1221",
        "1.3.1222"
      ],
      "withdraws": []
    }
  },
  "valid_worker": true,
  "valid_key": true,
  "took": 0.120231256998522
}
